Pre/Verilog_Circ/comp_cpu_checker/src.v
`timescale 1ns / 1ps
//////////////////////////////////////////////////////////////////////////////////
// Company: 
// Engineer: 
// 
// Create Date:    21:32:02 09/22/2021 
// Design Name: 
// Module Name:    cup_checker2 
// Project Name: 
// Target Devices: 
// Tool versions: 
// Description: 
//
// Dependencies: 
//
// Revision: 
// Revision 0.01 - File Created
// Additional Comments: 
//
//////////////////////////////////////////////////////////////////////////////////
module cpu_checker(
    input clk,
    input reset,
    input [7:0] char,
    input [15:0] freq,
    output [1:0] format_type,
    output [3:0] error_code
    );
    function isnum;
		 input [7:0] c;
		 begin
		 isnum = (c >= "0" && c <= "9");
	 end
	 endfunction
	 
	 function isx;
		 input [7:0] x;
		 begin
		 isx = ((x >= "0" && x <= "9")||(x >= "a" && x <= "f"));
	 end
	 endfunction
	 
	 function [3:0] xtoh;
		input [7:0] a;
		begin
		xtoh = (a >= "0" && a <= "9") ? (a - "0") : (a - "a" + 10);
		end
	 endfunction
	 
	 reg [4:0] s;
	 reg [3:0] times;
	 reg [20:0] T;
	 reg [20:0] gref;
	 reg [32:0] pc;
	 reg [32:0] addr;
	 reg e_time;
	 reg e_pc;
	 reg e_gref;
	 reg e_addr;
	 //wire [15:0] h_freq;
	 
	 initial begin
		s = 0;
		times = 0;
		T = 0;
		gref = 0;
		e_time = 0;
		e_pc = 0;
		e_gref = 0;
		e_addr = 0;
		pc = 0;
		addr = 0;
	 end
	 
	 always@(posedge clk) begin
		if(reset == 1) begin
			s <= 0;
			times <= 0;
			T <= 0;
			gref <= 0;
			e_time <= 0;
			e_pc <= 0;
			e_gref <= 0;
			e_addr <= 0;
			pc <= 0;
		   addr <= 0;
		end
		else begin
			case(s)
			0 : begin
			    times <= 0;
				 T <= 0;
				 gref <= 0;
				 e_time <= 0;
				 e_pc <= 0;
				 e_gref <= 0;
				 e_addr <= 0;
				 pc <= 0;
				 addr <= 0;
			    if(char == "^") s <= 1;
			    else s <= 0;
				 end
			1 : begin
			    gref <= 0;
				 pc <= 0;
		       addr <= 0;
				 e_pc <= 0;
				 e_gref <= 0;
				 e_addr <= 0;
			    if(isnum(char) && (times < 4)) begin     //time 10
					times <= times + 1;
					T <= (T << 3) + (T << 1) + char - "0";
					s <= 1;
					e_time <= 0;
				 end
			    else if(char == "@" && (times <= 4) && (times >= 1)) begin
					times <= 0;
					s <= 2;
					e_time <= ((T & ((freq >> 1) - 1)) != 0 ) ? 1 : 0;    //e_time
					//$display("fuck %d %b", e_time, T);
				 end
				 else begin
				   s <= 0;
					times <= 0;
				 end
				 end
			2 : if(isx(char) && (times < 8)) begin   //pc 16
					times <= times + 1;
					s <= 2;
					pc <= (pc << 4) + xtoh(char);
					end
				 else if((char == ":") && (times == 8)) begin
					times <= 0;
					s <= 3;
					e_pc = ~((pc >= 16'h3000) && (pc <= 16'h4fff) && ((pc & 2'b11) == 0));   //e_pc
				 end
 				 else begin
					 times <= 0;
					 s <= 0;
				 end
			3 : if(char == "0" || char == " ") s <= 3;
			    else if(char == "$") s <= 4;
				 else if(char ==8'd42) s<= 10;
				 else s <= 0;
			4 : if(isnum(char) && (times < 4)) begin     //grf 10
					times <= times + 1;
					s <= 4;
					gref <= (gref << 3) + (gref << 1) + char - "0";
				 end
				 else if((char == "0" || char == " ") && (times >= 1) && (times <= 4)) begin
					times <= 0;
					s <= 5;
				 end
				 else if((char == "<") && (times >= 1) && (times <= 4)) begin
					times <= 0;
					s <= 6;
				 end
				 else begin
					times <= 0;
					s <= 0;
				 end
			5 : if(char == "0" || char == " ") s <= 5;
			    else if(char == "<") s <=6;
				 else s <= 0;
			6 : begin
			    e_gref <= ~((gref <= 31) && (gref >= 0));   //e_gref
			    if(char == "=") s <= 7;
			    else s <= 0;
				 end
			7 : if(char == "0" || char == " ") s <= 7;
			    else if(isx(char)) begin
					times <= times + 1;
					s <= 8;
				 end
				 else s <= 0;
			8 : if(isx(char) && (times < 8)) begin
					times <= times + 1;
					s <= 8;
				 end
			    else if(char == "#" && times == 8) begin
					times <= 0;
					s <=9;
             end
             else begin
					times <=0;
					s <= 0;
				 end
			9 : begin
			    T<= 0;
			    if(char == "^") s <= 1;
			    else s<= 0;
				 end
			10 : if(isx(char) && (times < 8)) begin     //addr 16
					times <= times + 1;
					s <= 10;
					addr <= (addr << 4) + xtoh(char);
				  end
				  else if((char == "0" || char == " ") && times == 8) begin
					times <= 0;
					s <= 11;
				  end
				  else if(char == "<" && times == 8) begin
					times <= 0;
					s <= 12;
				  end
				  else begin
				  times <= 0;
				  s <= 0;
				  end
			11 : if(char == "0" || char == " ") s <= 11;
			     else if(char == "<") s <= 12;
				  else s <= 0;
			12 : begin
			     e_addr <= ~((addr >= 0) && (addr <= 16'h2fff) && (pc & 2'b11 == 0));   //e_addr
			     if(char == "=") s <= 13;
			     else s <= 0;
				  end
			13 : if(char == "0" || char == " ") s <= 13;
			     else if(isx(char)) begin
					  times <= times + 1;
					  s <= 14;
				  end
			14 : if(isx(char) && times < 8) begin     
					times <= times + 1;
					s <= 14;
				  end
				  else if(char == "#" && times == 8) begin
					times <= 0;
					s <= 15;
				  end
				  else begin
					  times <= 0;
					  s <= 0;
				  end
			15 : begin
			     T<=0;
			     if(char == "^") s <= 1;
			     else s<= 0;
				  end
			endcase
		end
	end
		assign format_type = (s == 9) ? 2'b01 :
		                     (s == 15) ? 2'b10 :
									2'b00;
		//assign h_freq = (freq >> 1) -1;
      assign error_code = (~(s == 9 || s == 15)) ? 4'b0000 : {e_gref,e_addr,e_pc,e_time};		

endmodule

Pre/Verilog_Circ/comp_cpu_checker/my_cpu_checker_tb.v
`timescale 1ns / 1ps
`include "std.v"

module tb;

	// Inputs
	reg clk;
	reg reset;
	reg [7:0] char;
	reg [15:0] freq;
	reg finish;

	// Outputs
	wire [1:0] format_type;
	wire [3:0] error_code;

   always @(posedge clk) begin
      if (!reset && !finish) begin
         $display("%d", format_type);
      end
   end

	// Instantiate the Unit Under Test (UUT)
	cpu_checker uut (
		.clk(clk),
		.reset(reset),
		.char(char), 
        .freq(16'd256),
		.format_type(format_type)
	);

	initial begin
		$dumpfile("cpu_checker_wave.vcd");
		$dumpvars;
		// Initialize Inputs
		clk = 0;
		reset = 1;
		char = 0;
		freq = 2;
		finish = 0;
		#10 reset = 0;
		#2 char = "^";
		#2 char = "8";
		#2 char = "5";
		#2 char = "5";
		#2 char = "2";
		#2 char = "@";
		#2 char = "0";
		#2 char = "0";
		#2 char = "0";
		#2 char = "0";
		#2 char = "a";
		#2 char = "1";
		#2 char = "9";
		#2 char = "b";
		#2 char = ":";
		#2 char = " ";
		#2 char = "*";
		#2 char = "0";
		#2 char = "0";
		#2 char = "0";
		#2 char = "0";
		#2 char = "f";
		#2 char = "d";
		#2 char = "5";
		#2 char = "5";
		#2 char = "<";
		#2 char = "=";
		#2 char = "0";
		#2 char = "0";
		#2 char = "0";
		#2 char = "0";
		#2 char = "3";
		#2 char = "5";
		#2 char = "d";
		#2 char = "e";
		#2 char = "#";
		#20
		finish = 1;
		$finish;
	end

    always #1 clk = ~clk;

endmodule

Pre/Verilog_Circ/comp_cpu_checker/dump.vcd
$date
	Thu Sep 23 00:19:11 2021
$end
$version
	Icarus Verilog
$end
$timescale
	1ps
$end
$scope module tb $end
$var wire 2 ! format_type [1:0] $end
$var wire 4 " error_code [3:0] $end
$var reg 8 # char [7:0] $end
$var reg 1 $ clk $end
$var reg 1 % finish $end
$var reg 16 & freq [15:0] $end
$var reg 1 ' reset $end
$scope module uut $end
$var wire 8 ( char [7:0] $end
$var wire 1 $ clk $end
$var wire 16 ) freq [15:0] $end
$var wire 1 ' reset $end
$var wire 2 * format_type [1:0] $end
$var wire 4 + error_code [3:0] $end
$var reg 21 , T [20:0] $end
$var reg 33 - addr [32:0] $end
$var reg 1 . e_addr $end
$var reg 1 / e_gref $end
$var reg 1 0 e_pc $end
$var reg 1 1 e_time $end
$var reg 21 2 gref [20:0] $end
$var reg 33 3 pc [32:0] $end
$var reg 5 4 s [4:0] $end
$var reg 4 5 times [3:0] $end
$scope function isnum $end
$var reg 8 6 c [7:0] $end
$upscope $end
$scope function isx $end
$var reg 8 7 x [7:0] $end
$upscope $end
$scope function xtoh $end
$var reg 8 8 a [7:0] $end
$upscope $end
$upscope $end
$upscope $end
$enddefinitions $end
#0
$dumpvars
bx 8
bx 7
bx 6
b0 5
b0 4
b0 3
b0 2
01
00
0/
0.
b0 -
b0 ,
b0 +
b0 *
b1000000000000 )
b0 (
1'
b10 &
0%
0$
b0 #
b0 "
b0 !
$end
#1000
1$
#2000
0$
#3000
1$
#4000
0$
#5000
1$
#6000
0$
#7000
1$
#8000
0$
#9000
1$
#10000
0$
0'
#11000
1$
#12000
0$
b1011110 #
b1011110 (
#13000
b1 4
1$
#14000
0$
b110010 #
b110010 (
#15000
b10 ,
b1 5
b110010 6
1$
#16000
0$
b1000000 #
b1000000 (
#17000
11
b10 4
b0 5
b1000000 6
1$
#18000
0$
b1100101 #
b1100101 (
#19000
b1110 3
b1 5
b1100101 8
b1100101 7
1$
#20000
0$
#21000
b11101110 3
b10 5
1$
#22000
0$
b110010 #
b110010 (
#23000
b111011100010 3
b11 5
b110010 8
b110010 7
1$
#24000
0$
b1100001 #
b1100001 (
#25000
b1110111000101010 3
b100 5
b1100001 8
b1100001 7
1$
#26000
0$
b111000 #
b111000 (
#27000
b11101110001010101000 3
b101 5
b111000 8
b111000 7
1$
#28000
0$
b1100101 #
b1100101 (
#29000
b111011100010101010001110 3
b110 5
b1100101 8
b1100101 7
1$
#30000
0$
#31000
b1110111000101010100011101110 3
b111 5
1$
#32000
0$
b111000 #
b111000 (
#33000
b11101110001010101000111011101000 3
b1000 5
b111000 8
b111000 7
1$
#34000
0$
b111010 #
b111010 (
#35000
b11 4
b0 5
10
b111010 7
1$
#36000
0$
b100000 #
b100000 (
#37000
1$
#38000
0$
b101010 #
b101010 (
#39000
b1010 4
1$
#40000
0$
b110001 #
b110001 (
#41000
b1 -
b1 5
b110001 8
b110001 7
1$
#42000
0$
b110110 #
b110110 (
#43000
b10110 -
b10 5
b110110 8
b110110 7
1$
#44000
0$
b110100 #
b110100 (
#45000
b101100100 -
b11 5
b110100 8
b110100 7
1$
#46000
0$
b110011 #
b110011 (
#47000
b1011001000011 -
b100 5
b110011 8
b110011 7
1$
#48000
0$
b1100010 #
b1100010 (
#49000
b10110010000111011 -
b101 5
b1100010 8
b1100010 7
1$
#50000
0$
b110110 #
b110110 (
#51000
b101100100001110110110 -
b110 5
b110110 8
b110110 7
1$
#52000
0$
b110010 #
b110010 (
#53000
b1011001000011101101100010 -
b111 5
b110010 8
b110010 7
1$
#54000
0$
b111001 #
b111001 (
#55000
b10110010000111011011000101001 -
b1000 5
b111001 8
b111001 7
1$
#56000
0$
b111100 #
b111100 (
#57000
b1100 4
b0 5
b111100 7
1$
#58000
0$
b111101 #
b111101 (
#59000
b1101 4
1.
1$
#60000
0$
b100000 #
b100000 (
#61000
1$
#62000
0$
b110111 #
b110111 (
#63000
b1110 4
b1 5
b110111 7
1$
#64000
0$
b111001 #
b111001 (
#65000
b10 5
b111001 7
1$
#66000
0$
b1100110 #
b1100110 (
#67000
b11 5
b1100110 7
1$
#68000
0$
b1100100 #
b1100100 (
#69000
b100 5
b1100100 7
1$
#70000
0$
b110001 #
b110001 (
#71000
b101 5
b110001 7
1$
#72000
0$
b1100100 #
b1100100 (
#73000
b110 5
b1100100 7
1$
#74000
0$
b1100110 #
b1100110 (
#75000
b111 5
b1100110 7
1$
#76000
0$
b110100 #
b110100 (
#77000
b1000 5
b110100 7
1$
#78000
0$
b100011 #
b100011 (
#79000
b111 "
b111 +
b10 !
b10 *
b1111 4
b0 5
b100011 7
1$
#80000
0$
b1011110 #
b1011110 (
#81000
b0 "
b0 +
b0 !
b0 *
b1 4
b0 ,
1$
#82000
0$
b111001 #
b111001 (
#83000
01
b1001 ,
b1 5
0.
00
b0 -
b0 3
b111001 6
1$
#84000
0$
b1000000 #
b1000000 (
#85000
11
b10 4
b0 5
b1000000 6
1$
#86000
0$
b111000 #
b111000 (
#87000
b1000 3
b1 5
b111000 8
b111000 7
1$
#88000
0$
#89000
b10001000 3
b10 5
1$
#90000
0$
b1100010 #
b1100010 (
#91000
b100010001011 3
b11 5
b1100010 8
b1100010 7
1$
#92000
0$
b110111 #
b110111 (
#93000
b1000100010110111 3
b100 5
b110111 8
b110111 7
1$
#94000
0$
b110110 #
b110110 (
#95000
b10001000101101110110 3
b101 5
b110110 8
b110110 7
1$
#96000
0$
b110010 #
b110010 (
#97000
b100010001011011101100010 3
b110 5
b110010 8
b110010 7
1$
#98000
0$
b110001 #
b110001 (
#99000
b1000100010110111011000100001 3
b111 5
b110001 8
b110001 7
1$
#100000
0$
b1100001 #
b1100001 (
#101000
b10001000101101110110001000011010 3
b1000 5
b1100001 8
b1100001 7
1$
#102000
0$
b111010 #
b111010 (
#103000
b11 4
b0 5
10
b111010 7
1$
#104000
0$
b101010 #
b101010 (
#105000
b1010 4
1$
#106000
0$
b110000 #
b110000 (
#107000
b1 5
b110000 8
b110000 7
1$
#108000
0$
b1100100 #
b1100100 (
#109000
b1101 -
b10 5
b1100100 8
b1100100 7
1$
#110000
0$
b1100001 #
b1100001 (
#111000
b11011010 -
b11 5
b1100001 8
b1100001 7
1$
#112000
0$
b1100011 #
b1100011 (
#113000
b110110101100 -
b100 5
b1100011 8
b1100011 7
1$
#114000
0$
b1100001 #
b1100001 (
#115000
b1101101011001010 -
b101 5
b1100001 8
b1100001 7
1$
#116000
0$
b110111 #
b110111 (
#117000
b11011010110010100111 -
b110 5
b110111 8
b110111 7
1$
#118000
0$
b1100001 #
b1100001 (
#119000
b110110101100101001111010 -
b111 5
b1100001 8
b1100001 7
1$
#120000
0$
b1100101 #
b1100101 (
#121000
b1101101011001010011110101110 -
b1000 5
b1100101 8
b1100101 7
1$
#122000
0$
b100000 #
b100000 (
#123000
b1011 4
b0 5
b100000 7
1$
#124000
0$
b111100 #
b111100 (
#125000
b1100 4
1$
#126000
0$
b111101 #
b111101 (
#127000
b1101 4
1.
1$
#128000
0$
b100000 #
b100000 (
#129000
1$
#130000
0$
b110000 #
b110000 (
#131000
1$
#132000
0$
b1100001 #
b1100001 (
#133000
b1110 4
b1 5
b1100001 7
1$
#134000
0$
b111000 #
b111000 (
#135000
b10 5
b111000 7
1$
#136000
0$
b1100001 #
b1100001 (
#137000
b11 5
b1100001 7
1$
#138000
0$
b110100 #
b110100 (
#139000
b100 5
b110100 7
1$
#140000
0$
b110110 #
b110110 (
#141000
b101 5
b110110 7
1$
#142000
0$
b110011 #
b110011 (
#143000
b110 5
b110011 7
1$
#144000
0$
b110000 #
b110000 (
#145000
b111 5
b110000 7
1$
#146000
0$
b100011 #
b100011 (
#147000
b0 4
b0 5
b100011 7
1$
#148000
0$
#149000
b0 -
b0 3
0.
00
01
b0 ,
1$
#150000
0$
#151000
1$
#152000
0$
#153000
1$
#154000
0$
#155000
1$
#156000
0$
#157000
1$
#158000
0$
#159000
1$
#160000
0$
#161000
1$
#162000
0$
#163000
1$
#164000
0$
#165000
1$
#166000
0$
1%
